Metadata-Version: 2.1
Name: related-without-future
Version: 0.7.4
Summary: Related: Straightforward nested object models in Python
Home-page: https://github.com/Antoni-Czaplicki/related-without-future
License: MIT license
Keywords: related object models yaml json dict nested
Classifier: Development Status :: 2 - Pre-Alpha
Classifier: Intended Audience :: Developers
Classifier: License :: OSI Approved :: MIT License
Classifier: Natural Language :: English
Classifier: Programming Language :: Python :: 3
Classifier: Programming Language :: Python :: 3.4
Classifier: Programming Language :: Python :: 3.5
Classifier: Programming Language :: Python :: 3.6
Classifier: Programming Language :: Python :: 3.7
Classifier: Programming Language :: Python :: 3.8
Classifier: Programming Language :: Python :: 3.9
Classifier: Programming Language :: Python :: 3.10
Classifier: Programming Language :: Python :: 3.11
Classifier: Programming Language :: Python :: 3.12
License-File: LICENSE
Requires-Dist: attrs >=19.3.0
Requires-Dist: PyYAML
Requires-Dist: python-dateutil
Requires-Dist: singledispatch ; python_version < "3.4"
